README.md
setup.py
notify/__init__.py
notify/client.py
notify/consts.py
notify_client.egg-info/PKG-INFO
notify_client.egg-info/SOURCES.txt
notify_client.egg-info/dependency_links.txt
notify_client.egg-info/requires.txt
notify_client.egg-info/top_level.txt