Metadata-Version: 1.0
Name: notify-client
Version: 0.0.3
Summary: Soft Way company notify service client.
Home-page: https://github.com/telminov/notify-client
Author: Telminov Sergey
Author-email: sergey@telminov.ru
License: The MIT License
Platform: UNKNOWN
